{
"Date": "2025/8/17 9:12:08",
"UnityVersion": "2022.3.48t7",
"com.unity.scriptablebuildpipeline": "1.21.25",
"com.unity.addressables": "1.22.3",
"traceEvents": [
{"name": "Building Default Build Script", "ph": "X", "dur": 2995505.9, "tid": 1, "ts": 132, "pid": 1}
,{"name": "ProcessAllGroups", "ph": "X", "dur": 23808.7, "tid": 1, "ts": 302, "pid": 1}
,{"name": "ContentPipeline.BuildAssetBundles", "ph": "X", "dur": 2903464.2, "tid": 1, "ts": 24236, "pid": 1}
,{"name": "AssetDatabase.SaveAssets", "ph": "X", "dur": 633.400000000002, "tid": 1, "ts": 52211, "pid": 1}
,{"name": "SwitchToBuildPlatform", "ph": "X", "dur": 19.5000000000007, "tid": 1, "ts": 54069, "pid": 1}
,{"name": "RebuildSpriteAtlasCache", "ph": "X", "dur": 1010.4, "tid": 1, "ts": 54174, "pid": 1}
,{"name": "BuildPlayerScripts", "ph": "X", "dur": 1264253.7, "tid": 1, "ts": 55268, "pid": 1}
,{"name": "PostScriptsCallback", "ph": "X", "dur": 5.40000000000873, "tid": 1, "ts": 1320182, "pid": 1}
,{"name": "CalculateSceneDependencyData", "ph": "X", "dur": 405041, "tid": 1, "ts": 1320369, "pid": 1}
,{"name": "LoadCachedData", "ph": "X", "dur": 563.599999999951, "tid": 1, "ts": 1320487, "pid": 1, "args": {"0":"1 items", "1":"Time spent deserializing: 0ms", "2":"Local Cache hit count: 0"}}
,{"name": "Read and deserialize cache info", "ph": "X", "dur": 537.100000000009, "tid": 1, "ts": 1320500, "pid": 1}
,{"name": "Check for changed dependencies", "ph": "X", "dur": 9.20000000019172, "tid": 1, "ts": 1321052, "pid": 1, "args": {"0":"Unchanged dependencies count: 0"}}
,{"name": "Calculate Scene Dependencies", "ph": "X", "dur": 378558.2, "tid": 1, "ts": 1321066, "pid": 1, "args": {"0":"f151cbffb20a54c4b89cfab70132c4e0"}}
,{"name": "SaveCachedData", "ph": "X", "dur": 25734.6, "tid": 1, "ts": 1699658, "pid": 1, "args": {"0":"Saving 1 infos"}}
,{"name": "SerializingCacheInfos[1]", "ph": "X", "dur": 25607.3000000001, "tid": 1, "ts": 1699780, "pid": 1}
,{"name": "CalculateAssetDependencyData", "ph": "X", "dur": 35398.7000000002, "tid": 1, "ts": 1726074, "pid": 1, "args": {"0":"ca9f5fa95ffab41fb9a615ab714db018", "1":"dff4dbf0b73f7dc4b8e60130019432ca", "2":"55a744c034e74fe49bb452b5c96aad2f", "3":"b781c2a13ff629746aebda98486e5be8", "4":"16e126a8ff9a374498545c110b39e17d", "5":"7609c3dc843e63445996c6d24ba6ed1d"}}
,{"name": "Gathering Cache Entries to Load", "ph": "X", "dur": 2116.59999999983, "tid": 1, "ts": 1726083, "pid": 1}
,{"name": "LoadCachedData", "ph": "X", "dur": 902.199999999993, "tid": 1, "ts": 1727290, "pid": 1, "args": {"0":"6 items", "1":"Time spent deserializing: 0ms", "2":"Local Cache hit count: 0"}}
,{"name": "Read and deserialize cache info", "ph": "X", "dur": 875.19999999995, "tid": 1, "ts": 1727305, "pid": 1}
,{"name": "Check for changed dependencies", "ph": "X", "dur": 6.60000000016225, "tid": 1, "ts": 1728193, "pid": 1, "args": {"0":"Unchanged dependencies count: 0"}}
,{"name": "Calculate Asset Dependencies", "ph": "X", "dur": 37.900000000036, "tid": 1, "ts": 1728214, "pid": 1}
,{"name": "Calculate Asset Dependencies", "ph": "X", "dur": 528.800000000047, "tid": 1, "ts": 1728254, "pid": 1}
,{"name": "Calculate Asset Dependencies", "ph": "X", "dur": 366.899999999987, "tid": 1, "ts": 1728784, "pid": 1}
,{"name": "Calculate Asset Dependencies", "ph": "X", "dur": 326.299999999947, "tid": 1, "ts": 1729152, "pid": 1}
,{"name": "Calculate Asset Dependencies", "ph": "X", "dur": 372.600000000148, "tid": 1, "ts": 1729480, "pid": 1}
,{"name": "Calculate Asset Dependencies", "ph": "X", "dur": 340.50000000002, "tid": 1, "ts": 1729855, "pid": 1}
,{"name": "Gathering Cache Entries to Save", "ph": "X", "dur": 25835.2, "tid": 1, "ts": 1735519, "pid": 1}
,{"name": "SaveCachedData", "ph": "X", "dur": 22959.4, "tid": 1, "ts": 1738394, "pid": 1, "args": {"0":"Saving 6 infos"}}
,{"name": "SerializingCacheInfos[6]", "ph": "X", "dur": 22837.9, "tid": 1, "ts": 1738510, "pid": 1}
,{"name": "AddHashToBundleNameTask", "ph": "X", "dur": 3.79999999995562, "tid": 1, "ts": 1761878, "pid": 1}
,{"name": "StripUnusedSpriteSources", "ph": "X", "dur": 2.99999999992906, "tid": 1, "ts": 1762022, "pid": 1}
,{"name": "CreateBuiltInShadersBundle", "ph": "X", "dur": 39.4000000001142, "tid": 1, "ts": 1762181, "pid": 1}
,{"name": "PostDependencyCallback", "ph": "X", "dur": 2.1999999999025, "tid": 1, "ts": 1762349, "pid": 1}
,{"name": "GenerateBundlePacking", "ph": "X", "dur": 1097.70000000003, "tid": 1, "ts": 1762508, "pid": 1}
,{"name": "UpdateBundleObjectLayout", "ph": "X", "dur": 2.90000000018154, "tid": 1, "ts": 1763782, "pid": 1}
,{"name": "GenerateBundleCommands", "ph": "X", "dur": 3903.19999999997, "tid": 1, "ts": 1763947, "pid": 1}
,{"name": "GenerateSubAssetPathMaps", "ph": "X", "dur": 86.5999999998621, "tid": 1, "ts": 1768086, "pid": 1}
,{"name": "GenerateBundleMaps", "ph": "X", "dur": 109.099999999899, "tid": 1, "ts": 1768308, "pid": 1}
,{"name": "Temporary Map Creations", "ph": "X", "dur": 64.600000000155, "tid": 1, "ts": 1768310, "pid": 1}
,{"name": "Populate BuildReferenceMaps", "ph": "X", "dur": 16.4999999999509, "tid": 1, "ts": 1768376, "pid": 1}
,{"name": "Populate BuildUsageTagSet", "ph": "X", "dur": 22.6999999999862, "tid": 1, "ts": 1768394, "pid": 1}
,{"name": "PostPackingCallback", "ph": "X", "dur": 5.09999999985666, "tid": 1, "ts": 1768574, "pid": 1}
,{"name": "WriteSerializedFiles", "ph": "X", "dur": 453563.6, "tid": 1, "ts": 1768784, "pid": 1}
,{"name": "RunCachedOperation", "ph": "X", "dur": 453548, "tid": 1, "ts": 1768799, "pid": 1, "args": {"0":"Total Entries: 3, Processed: 3, Cached: 0"}}
,{"name": "Creating Cache Entries", "ph": "X", "dur": 20669.9000000001, "tid": 1, "ts": 1768801, "pid": 1}
,{"name": "GetCacheEntry", "ph": "X", "dur": 18497.0000000001, "tid": 1, "ts": 1768804, "pid": 1, "args": {"0":"CAB-bcd924c70f18614adeb35568aabd03ac"}}
,{"name": "Gather Objects AssetBundleWriteOperation", "ph": "X", "dur": 13099.0999999999, "tid": 1, "ts": 1768855, "pid": 1, "args": {"0":"CAB-bcd924c70f18614adeb35568aabd03ac"}}
,{"name": "Hashing Command", "ph": "X", "dur": 529.800000000023, "tid": 1, "ts": 1781961, "pid": 1, "args": {"0":"CAB-bcd924c70f18614adeb35568aabd03ac"}}
,{"name": "Hashing UsageSet", "ph": "X", "dur": 4.59999999998217, "tid": 1, "ts": 1782493, "pid": 1, "args": {"0":"CAB-bcd924c70f18614adeb35568aabd03ac"}}
,{"name": "Hashing ReferenceMap", "ph": "X", "dur": 8.80000000006476, "tid": 1, "ts": 1782498, "pid": 1, "args": {"0":"CAB-bcd924c70f18614adeb35568aabd03ac"}}
,{"name": "Hashing Info", "ph": "X", "dur": 2952, "tid": 1, "ts": 1782508, "pid": 1, "args": {"0":"CAB-bcd924c70f18614adeb35568aabd03ac"}}
,{"name": "Hashing Objects", "ph": "X", "dur": 1633.29999999996, "tid": 1, "ts": 1785461, "pid": 1, "args": {"0":"CAB-bcd924c70f18614adeb35568aabd03ac"}}
,{"name": "GetCacheEntry", "ph": "X", "dur": 1122.49999999995, "tid": 1, "ts": 1787306, "pid": 1, "args": {"0":"CAB-c98b4f8ee63af38712a486110f5d883d"}}
,{"name": "Gather Objects AssetBundleWriteOperation", "ph": "X", "dur": 307.099999999991, "tid": 1, "ts": 1787357, "pid": 1, "args": {"0":"CAB-c98b4f8ee63af38712a486110f5d883d"}}
,{"name": "Hashing Command", "ph": "X", "dur": 123.500000000149, "tid": 1, "ts": 1787666, "pid": 1, "args": {"0":"CAB-c98b4f8ee63af38712a486110f5d883d"}}
,{"name": "Hashing UsageSet", "ph": "X", "dur": 6.99999999983447, "tid": 1, "ts": 1787791, "pid": 1, "args": {"0":"CAB-c98b4f8ee63af38712a486110f5d883d"}}
,{"name": "Hashing ReferenceMap", "ph": "X", "dur": 6.50000000018736, "tid": 1, "ts": 1787799, "pid": 1, "args": {"0":"CAB-c98b4f8ee63af38712a486110f5d883d"}}
,{"name": "Hashing Info", "ph": "X", "dur": 114.500000000135, "tid": 1, "ts": 1787807, "pid": 1, "args": {"0":"CAB-c98b4f8ee63af38712a486110f5d883d"}}
,{"name": "Hashing Objects", "ph": "X", "dur": 267.200000000003, "tid": 1, "ts": 1787923, "pid": 1, "args": {"0":"CAB-c98b4f8ee63af38712a486110f5d883d"}}
,{"name": "GetCacheEntry", "ph": "X", "dur": 1035.20000000003, "tid": 1, "ts": 1788435, "pid": 1, "args": {"0":"CAB-514d39fe739573cad5743654f30f4eb0.sharedAssets"}}
,{"name": "Gather Objects", "ph": "X", "dur": 99.7999999999593, "tid": 1, "ts": 1788560, "pid": 1, "args": {"0":"CAB-514d39fe739573cad5743654f30f4eb0.sharedAssets"}}
,{"name": "Hashing Command", "ph": "X", "dur": 64.4999999999527, "tid": 1, "ts": 1788664, "pid": 1, "args": {"0":"CAB-514d39fe739573cad5743654f30f4eb0.sharedAssets"}}
,{"name": "Hashing UsageSet", "ph": "X", "dur": 3.69999999998072, "tid": 1, "ts": 1788731, "pid": 1, "args": {"0":"CAB-514d39fe739573cad5743654f30f4eb0.sharedAssets"}}
,{"name": "Hashing ReferenceMap", "ph": "X", "dur": 8.40000000016516, "tid": 1, "ts": 1788740, "pid": 1, "args": {"0":"CAB-514d39fe739573cad5743654f30f4eb0.sharedAssets"}}
,{"name": "Hashing PreloadInfo", "ph": "X", "dur": 38.9999999999873, "tid": 1, "ts": 1788750, "pid": 1, "args": {"0":"CAB-514d39fe739573cad5743654f30f4eb0.sharedAssets"}}
,{"name": "Hashing Info", "ph": "X", "dur": 33.7999999999283, "tid": 1, "ts": 1788791, "pid": 1, "args": {"0":"CAB-514d39fe739573cad5743654f30f4eb0.sharedAssets"}}
,{"name": "Hashing Objects", "ph": "X", "dur": 99.1999999998825, "tid": 1, "ts": 1788826, "pid": 1, "args": {"0":"CAB-514d39fe739573cad5743654f30f4eb0.sharedAssets"}}
,{"name": "Load Cached Data", "ph": "X", "dur": 693.500000000085, "tid": 1, "ts": 1789478, "pid": 1}
,{"name": "LoadCachedData", "ph": "X", "dur": 676.400000000058, "tid": 1, "ts": 1789480, "pid": 1, "args": {"0":"3 items", "1":"Time spent deserializing: 0ms", "2":"Local Cache hit count: 0"}}
,{"name": "Read and deserialize cache info", "ph": "X", "dur": 645.200000000159, "tid": 1, "ts": 1789492, "pid": 1}
,{"name": "Check for changed dependencies", "ph": "X", "dur": 11.4999999998417, "tid": 1, "ts": 1790158, "pid": 1, "args": {"0":"Unchanged dependencies count: 0"}}
,{"name": "Process Entries", "ph": "X", "dur": 416525.3, "tid": 1, "ts": 1790189, "pid": 1}
,{"name": "Writing AssetBundleWriteOperation", "ph": "X", "dur": 9351.49999999999, "tid": 1, "ts": 1792238, "pid": 1, "args": {"0":"CAB-bcd924c70f18614adeb35568aabd03ac"}}
,{"name": "Writing AssetBundleWriteOperation", "ph": "X", "dur": 10056.2, "tid": 1, "ts": 1804293, "pid": 1, "args": {"0":"CAB-c98b4f8ee63af38712a486110f5d883d"}}
,{"name": "Writing SceneBundleWriteOperation", "ph": "X", "dur": 370595.4, "tid": 1, "ts": 1834490, "pid": 1, "args": {"0":"CAB-514d39fe739573cad5743654f30f4eb0.sharedAssets"}}
,{"name": "Process Cached Entries", "ph": "X", "dur": 3.69999999975335, "tid": 1, "ts": 2206719, "pid": 1}
,{"name": "Saving to Cache", "ph": "X", "dur": 15593.0000000003, "tid": 1, "ts": 2206740, "pid": 1}
,{"name": "Creating Cached Infos", "ph": "X", "dur": 27.1000000002459, "tid": 1, "ts": 2206742, "pid": 1}
,{"name": "SaveCachedData", "ph": "X", "dur": 15556.5000000001, "tid": 1, "ts": 2206776, "pid": 1, "args": {"0":"Saving 3 infos"}}
,{"name": "SerializingCacheInfos[3]", "ph": "X", "dur": 15461.6000000001, "tid": 1, "ts": 2206866, "pid": 1}
,{"name": "ArchiveAndCompressBundles", "ph": "X", "dur": 353460.3, "tid": 1, "ts": 2223020, "pid": 1}
,{"name": "CreateWorkItems", "ph": "X", "dur": 81.300000000283, "tid": 1, "ts": 2223033, "pid": 1}
,{"name": "Creating Cache Entries", "ph": "X", "dur": 301.400000000285, "tid": 1, "ts": 2223116, "pid": 1}
,{"name": "Load Cached Data", "ph": "X", "dur": 614.000000000033, "tid": 1, "ts": 2223420, "pid": 1}
,{"name": "LoadCachedData", "ph": "X", "dur": 599.899999999707, "tid": 1, "ts": 2223423, "pid": 1, "args": {"0":"3 items", "1":"Time spent deserializing: 0ms", "2":"Local Cache hit count: 0"}}
,{"name": "Read and deserialize cache info", "ph": "X", "dur": 567.399999999907, "tid": 1, "ts": 2223443, "pid": 1}
,{"name": "Check for changed dependencies", "ph": "X", "dur": 8.60000000011496, "tid": 1, "ts": 2224024, "pid": 1, "args": {"0":"Unchanged dependencies count: 0"}}
,{"name": "CopyingCachedFiles", "ph": "X", "dur": 2.1999999999025, "tid": 1, "ts": 2224226, "pid": 1}
,{"name": "ArchiveItems", "ph": "X", "dur": 343510.4, "tid": 1, "ts": 2224229, "pid": 1, "args": {"0":"Archiving 3 Bundles"}}
,{"name": "ArchiveSingleItem", "ph": "X", "dur": 9044.7, "tid": 689, "ts": 2224268, "pid": 1, "args": {"0":"361bd3cd8d51d74e3ca10bbea1140f03.bundle"}}
,{"name": "Copying From Cache", "ph": "X", "dur": 1247, "tid": 689, "ts": 2232065, "pid": 1, "args": {"0":"E:\\WorkProject\\BaZiClient\\test_unity\\Library\\BuildCache\\f6\\f63e8725e4d9e33bd86727025be24d03\\2f1bdc85d6348c247cb8001df222d2a6\\50cb47c4ad2810156e179af1ca426105 -> E:\\WorkProject\\BaZiClient\\test_unity\\Temp\\com.unity.addressables\\AssetBundles\\361bd3cd8d51d74e3ca10bbea1140f03.bundle"}}
,{"name": "ArchiveSingleItem", "ph": "X", "dur": 9158.5, "tid": 684, "ts": 2224272, "pid": 1, "args": {"0":"fa963b2f683cce74ce98f10c7eed7a5c.bundle"}}
,{"name": "Copying From Cache", "ph": "X", "dur": 1147.7, "tid": 684, "ts": 2232282, "pid": 1, "args": {"0":"E:\\WorkProject\\BaZiClient\\test_unity\\Library\\BuildCache\\96\\96db1b02e1673e49c96a70d645ee8554\\3a7cf582f7c88075f72a887eebfe915c\\bcd924c70f18614adeb35568aabd03ac -> E:\\WorkProject\\BaZiClient\\test_unity\\Temp\\com.unity.addressables\\AssetBundles\\fa963b2f683cce74ce98f10c7eed7a5c.bundle"}}
,{"name": "ArchiveSingleItem", "ph": "X", "dur": 342874, "tid": 681, "ts": 2224260, "pid": 1, "args": {"0":"fb0411dcebeee0fd4970cb1b4ee4ae58.bundle"}}
,{"name": "Copying From Cache", "ph": "X", "dur": 1867.50000000001, "tid": 681, "ts": 2565265, "pid": 1, "args": {"0":"E:\\WorkProject\\BaZiClient\\test_unity\\Library\\BuildCache\\53\\537c470062db08e4d9bcec9c425b44ab\\1afe36beb29386490d10c160acd4a889\\c98b4f8ee63af38712a486110f5d883d -> E:\\WorkProject\\BaZiClient\\test_unity\\Temp\\com.unity.addressables\\AssetBundles\\fb0411dcebeee0fd4970cb1b4ee4ae58.bundle"}}
,{"name": "PostArchiveProcessing", "ph": "X", "dur": 168.099999999868, "tid": 1, "ts": 2567768, "pid": 1}
,{"name": "Copying To Cache", "ph": "X", "dur": 8522.99999999968, "tid": 1, "ts": 2567938, "pid": 1}
,{"name": "SaveCachedData", "ph": "X", "dur": 8510.30000000037, "tid": 1, "ts": 2567950, "pid": 1, "args": {"0":"Saving 3 infos"}}
,{"name": "SerializingCacheInfos[3]", "ph": "X", "dur": 8424.49999999963, "tid": 1, "ts": 2568027, "pid": 1}
,{"name": "GenerateLocationListsTask", "ph": "X", "dur": 4395.30000000013, "tid": 1, "ts": 2576787, "pid": 1}
,{"name": "Calculate Bundle Dependencies", "ph": "X", "dur": 42.8000000001703, "tid": 1, "ts": 2576820, "pid": 1}
,{"name": "ExpandDependencies", "ph": "X", "dur": 14.2000000000735, "tid": 1, "ts": 2576864, "pid": 1}
,{"name": "Calculate Locations", "ph": "X", "dur": 3951.19999999997, "tid": 1, "ts": 2577138, "pid": 1}
,{"name": "PostWritingCallback", "ph": "X", "dur": 4.10000000010768, "tid": 1, "ts": 2581431, "pid": 1}
,{"name": "ExtractDataTask", "ph": "X", "dur": 3.3000000003085, "tid": 1, "ts": 2581645, "pid": 1}
,{"name": "PostProcessBundles", "ph": "X", "dur": 7093.9999999996, "tid": 1, "ts": 2927710, "pid": 1}
,{"name": "Default Local Group", "ph": "X", "dur": 2822.00000000012, "tid": 1, "ts": 2928027, "pid": 1}
,{"name": "Move File", "ph": "X", "dur": 1984.69999999998, "tid": 1, "ts": 2928841, "pid": 1, "args": {"0":"Temp/com.unity.addressables/AssetBundles\\fa963b2f683cce74ce98f10c7eed7a5c.bundle -> Library/com.unity.addressables/aa/Android/Android\\defaultlocalgroup_assets_all_f70ccf80076c0487491766ae90a32f51.bundle"}}
,{"name": "Remote_Dll", "ph": "X", "dur": 1734.30000000008, "tid": 1, "ts": 2930854, "pid": 1}
,{"name": "Move File", "ph": "X", "dur": 1453.99999999972, "tid": 1, "ts": 2931129, "pid": 1, "args": {"0":"Temp/com.unity.addressables/AssetBundles\\fb0411dcebeee0fd4970cb1b4ee4ae58.bundle -> ServerData/Android\\remote_dll_assets_all_1d405b7520a20fd1096b11fbd8b7a141.bundle"}}
,{"name": "Remote_Scene", "ph": "X", "dur": 1625.30000000015, "tid": 1, "ts": 2932593, "pid": 1}
,{"name": "Move File", "ph": "X", "dur": 1361.59999999973, "tid": 1, "ts": 2932851, "pid": 1, "args": {"0":"Temp/com.unity.addressables/AssetBundles\\361bd3cd8d51d74e3ca10bbea1140f03.bundle -> ServerData/Android\\remote_scene_scenes_all_aedbc44408a27d58e46ab6ba857793a1.bundle"}}
,{"name": "Process Catalog Entries", "ph": "X", "dur": 2698.39999999976, "tid": 1, "ts": 2934806, "pid": 1}
,{"name": "Generate JSON Catalog", "ph": "X", "dur": 1872.09999999959, "tid": 1, "ts": 2937505, "pid": 1}
,{"name": "Generating Json", "ph": "X", "dur": 133.200000000215, "tid": 1, "ts": 2938050, "pid": 1}
,{"name": "Hashing Catalog", "ph": "X", "dur": 332.700000000386, "tid": 1, "ts": 2938185, "pid": 1}
,{"name": "Generate link", "ph": "X", "dur": 1869.89999999969, "tid": 1, "ts": 2939379, "pid": 1}
,{"name": "Generate Settings", "ph": "X", "dur": 689.699999999903, "tid": 1, "ts": 2941261, "pid": 1}
,{"name": "Generate Content Update State", "ph": "X", "dur": 3030.8, "tid": 1, "ts": 2941952, "pid": 1}
,{"name": "Get Assets", "ph": "X", "dur": 79.4000000000779, "tid": 1, "ts": 2941955, "pid": 1}
,{"name": "Generate Build Layout", "ph": "X", "dur": 13811.6, "tid": 1, "ts": 2945283, "pid": 1}
,{"name": "BuildLayoutGenerationTask", "ph": "X", "dur": 13502.7, "tid": 1, "ts": 2945505, "pid": 1}
,{"name": "Generate Lookup tables", "ph": "X", "dur": 1711.60000000009, "tid": 1, "ts": 2945508, "pid": 1}
,{"name": "Generate Build Layout", "ph": "X", "dur": 1588.90000000019, "tid": 1, "ts": 2947221, "pid": 1}
,{"name": "Generate Basic Information", "ph": "X", "dur": 340.700000000197, "tid": 1, "ts": 2947294, "pid": 1}
,{"name": "Correlate Bundles to groups", "ph": "X", "dur": 171.799999999621, "tid": 1, "ts": 2948526, "pid": 1}
,{"name": "Apply Addressable info to layout data", "ph": "X", "dur": 64.5000000004075, "tid": 1, "ts": 2948699, "pid": 1}
,{"name": "Process additional bundle data", "ph": "X", "dur": 22.6000000002387, "tid": 1, "ts": 2948764, "pid": 1}
,{"name": "Generating implicit inclusion data", "ph": "X", "dur": 2.1999999999025, "tid": 1, "ts": 2948788, "pid": 1}
,{"name": "Writing BuildReport File", "ph": "X", "dur": 1769.20000000018, "tid": 1, "ts": 2948824, "pid": 1}
]
}
